xendpalmagic/__init__.py
xendpalmagic/core.py
xendpalmagic/exceptions.py
xendpalmagic/signatures.py
xendpalmagic-0.0.5.dist-info/LICENSE
xendpalmagic-0.0.5.dist-info/METADATA
xendpalmagic-0.0.5.dist-info/WHEEL
xendpalmagic-0.0.5.dist-info/top_level.txt
xendpalmagic-0.0.5.dist-info/RECORD
