Metadata-Version: 2.1
Name: xendpalmagic
Version: 0.0.5
Summary: Xendpalmagic: Advanced File Type Detection Library
Home-page: https://github.com/joeygoesgrey/xendpal-magic
Author: joeygoesgrey
Author-email: mail@godfreydjoseph@gmail.com
License: MIT
Project-URL: Documentation, https://github.com/joeygoesgrey/xendpal-magic#readme
Project-URL: Source, https://github.com/joeygoesgrey/xendpal-magic
Project-URL: Tracker, https://github.com/joeygoesgrey/xendpal-magic/issues
Keywords: file type detection,file signatures,MIME type,content analysis,python,file handling,file identification,magic numbers,file metadata
Classifier: Development Status :: 4 - Beta
Classifier: Intended Audience :: Developers
Classifier: Topic :: Software Development :: Libraries :: Python Modules
Classifier: License :: OSI Approved :: MIT License
Classifier: Programming Language :: Python :: 3
Classifier: Programming Language :: Python :: 3.6
Classifier: Programming Language :: Python :: 3.7
Classifier: Programming Language :: Python :: 3.8
Classifier: Programming Language :: Python :: 3.9
Classifier: Programming Language :: Python :: 3.10
Classifier: Operating System :: OS Independent
Requires-Python: >=3.6
License-File: LICENSE
